LICENSE
pyproject.toml
weneda/__init__.py
weneda/compose.py
weneda/font.py
weneda/formatter.py
weneda/placeholder.py
weneda-0.2.1.dist-info/LICENSE
weneda-0.2.1.dist-info/METADATA
weneda-0.2.1.dist-info/WHEEL
weneda-0.2.1.dist-info/RECORD
