Metadata-Version: 2.1
Name: weneda
Version: 0.2.1
Summary: Module for editing and formatting text.
Home-page: https://github.com/eeemoon/weneda
License: MIT
Author: EeeMoon
Requires-Python: >=3.10,<4.0
Classifier: License :: OSI Approved :: MIT License
Classifier: Programming Language :: Python :: 3
Classifier: Programming Language :: Python :: 3.10
Classifier: Programming Language :: Python :: 3.11
Classifier: Programming Language :: Python :: 3.12
Requires-Dist: fonttools
